djscript.py
ni_iotrace.py
setup.py
AnritsuTools/__init__.py
AnritsuTools/djscript.py
AnritsuTools/ni_iotrace.py
AnritsuTools.egg-info/PKG-INFO
AnritsuTools.egg-info/SOURCES.txt
AnritsuTools.egg-info/dependency_links.txt
AnritsuTools.egg-info/top_level.txt