Metadata-Version: 1.0
Name: AnritsuTools
Version: 1.0.4
Summary: Script running for Anritsu VNAs
Home-page: UNKNOWN
Author: David Judge
Author-email: djudge@anritsu.com
License: UNKNOWN
Platform: UNKNOWN
